<?xml version="1.0" encoding="UTF-8"?>
<!-- generated: 2019-09-19 11:37:00.556973 -->
<!-- generated by: tanaka -->
<!-- generator: python -->
<adag xmlns="http://pegasus.isi.edu/schema/DAX" xmlns:xsi="http://www.w3.org/2001/XMLSchema-instance" xsi:schemaLocation="http://pegasus.isi.edu/schema/DAX http://pegasus.isi.edu/schema/dax-3.6.xsd" version="3.6" name="forkJoin">
	<metadata key="dax.api">python</metadata>
	<file name="initial_input_file_2"/>
	<file name="initial_input_file_1"/>
	<file name="final_output_file"/>
	<file name="parent_output_file_3"/>
	<file name="child_3_output_file"/>
	<file name="parent_output_file_1"/>
	<file name="parent_output_file_2"/>
	<file name="child_2_output_file"/>
	<file name="child_1_output_file"/>
	<executable name="child"/>
	<executable name="initialProcess"/>
	<executable name="finalProcess"/>
	<job id="ID0000001" name="initialProcess">
		<uses name="initial_input_file_1" link="input"/>
		<uses name="initial_input_file_2" link="input"/>
		<uses name="parent_output_file_1" link="output"/>
		<uses name="parent_output_file_3" link="output"/>
		<uses name="parent_output_file_2" link="output"/>
	</job>
	<job id="ID0000002" name="child">
		<uses name="parent_output_file_1" link="input"/>
		<uses name="child_1_output_file" link="output"/>
	</job>
	<job id="ID0000003" name="child">
		<uses name="parent_output_file_2" link="input"/>
		<uses name="child_2_output_file" link="output"/>
	</job>
	<job id="ID0000004" name="child">
		<uses name="parent_output_file_3" link="input"/>
		<uses name="child_3_output_file" link="output"/>
	</job>
	<job id="ID0000005" name="finalProcess">
		<uses name="child_2_output_file" link="input"/>
		<uses name="child_3_output_file" link="input"/>
		<uses name="child_1_output_file" link="input"/>
		<uses name="final_output_file" link="output"/>
	</job>
	<child ref="ID0000002">
		<parent ref="ID0000001"/>
	</child>
	<child ref="ID0000003">
		<parent ref="ID0000001"/>
	</child>
	<child ref="ID0000004">
		<parent ref="ID0000001"/>
	</child>
	<child ref="ID0000005">
		<parent ref="ID0000002"/>
		<parent ref="ID0000003"/>
		<parent ref="ID0000004"/>
	</child>
</adag>
